CHANGES.txt
LICENSE.txt
MANIFEST.in
README.txt
setup.py
django_http_status.egg-info/PKG-INFO
django_http_status.egg-info/SOURCES.txt
django_http_status.egg-info/dependency_links.txt
django_http_status.egg-info/not-zip-safe
django_http_status.egg-info/requires.txt
django_http_status.egg-info/top_level.txt
http_status/__init__.py
http_status/unofficial.py